pyopenfigi/__init__.py
pyopenfigi/exceptions.py
pyopenfigi/models.py
pyopenfigi/wrapper.py
pyopenfigi-0.1.0.dist-info/LICENSE
pyopenfigi-0.1.0.dist-info/METADATA
pyopenfigi-0.1.0.dist-info/WHEEL
pyopenfigi-0.1.0.dist-info/top_level.txt
pyopenfigi-0.1.0.dist-info/RECORD
