Metadata-Version: 2.1
Name: pyopenfigi
Version: 0.1.0
Summary: Python wrapper for the OpenFIGI API
Author: tlouarn
License: MIT License
Project-URL: Homepage, https://github.com/tlouarn/pyopenfigi
Keywords: openfigi,api,bloomberg,figi,python
Classifier: License :: OSI Approved :: MIT License
Classifier: Programming Language :: Python
Classifier: Programming Language :: Python :: 3
Requires-Python: >=3.10
License-File: LICENSE
Requires-Dist: requests
Requires-Dist: pydantic (>=1.10)
Provides-Extra: dev
Requires-Dist: pytest ; extra == 'dev'
Requires-Dist: pytest-recording ; extra == 'dev'
